audioprep/__init__.py
audioprep/duration.py
audioprep/resample.py
audioprep/silence.py
audioprep-1.1.5.dist-info/METADATA
audioprep-1.1.5.dist-info/WHEEL
audioprep-1.1.5.dist-info/top_level.txt
audioprep-1.1.5.dist-info/RECORD
