Metadata-Version: 2.1
Name: audioprep
Version: 1.1.5
Summary: AI audio preparation tools, including audio trimming, duration calculation, and subtitle correction.
Author: abo123456789
Author-email: abcdef123456chen@sohu.com
Maintainer: abo123456789
Maintainer-email: abcdef123456chen@sohu.com
License: MIT License
Keywords: audio,audio processing,audio trimming,audio duration,subtitle correction,AI tools
Platform: all
Classifier: Development Status :: 4 - Beta
Classifier: Operating System :: OS Independent
Classifier: Intended Audience :: Developers
Classifier: License :: OSI Approved :: MIT License
Classifier: Programming Language :: Python
Classifier: Programming Language :: Python :: Implementation
Classifier: Programming Language :: Python :: 3.6
Classifier: Programming Language :: Python :: 3.7
Classifier: Programming Language :: Python :: 3.8
Classifier: Programming Language :: Python :: 3.9
Classifier: Programming Language :: Python :: 3.10
Classifier: Programming Language :: Python :: 3.11
Classifier: Topic :: Software Development :: Libraries
Requires-Dist: pydub >=0.25.1
Requires-Dist: librosa >=0.10.0
